xoinvader/__init__.py
xoinvader/animation.py
xoinvader/app.py
xoinvader/background.py
xoinvader/charge.py
xoinvader/collision.py
xoinvader/common.py
xoinvader/config/charges.json
xoinvader/config/path.json
xoinvader/config/ships.json
xoinvader/config/weapons.json
xoinvader/config/xoinvader.toml
xoinvader/constants.py
xoinvader/ecs.py
xoinvader/game.py
xoinvader/gui.py
xoinvader/handlers.py
xoinvader/ingame.py
xoinvader/keys.py
xoinvader/level.py
xoinvader/menu.py
xoinvader/render.py
xoinvader/res/gfx/ship.png
xoinvader/res/gfx/ship1.png
xoinvader/res/level1.bg
xoinvader/res/lucky-escape.ev
xoinvader/res/lucky-escape.lv
xoinvader/res/lucky-escape.toml
xoinvader/res/tgfx/playership.tgfx
xoinvader/scoreboard.py
xoinvader/ship.py
xoinvader/style.py
xoinvader/tests/__init__.py
xoinvader/tests/common.py
xoinvader/tests/conftest.py
xoinvader/tests/fixtures/chunk_duplicate_names.bg
xoinvader/tests/fixtures/chunk_no_name.bg
xoinvader/tests/fixtures/chunk_normal.bg
xoinvader/tests/fixtures/no_chunks.bg
xoinvader/tests/fixtures/scoreboard_corrupted
xoinvader/tests/fixtures/scoreboard_empty
xoinvader/tests/fixtures/scoreboard_valid
xoinvader/tests/test_animation.py
xoinvader/tests/test_background.py
xoinvader/tests/test_collision.py
xoinvader/tests/test_handlers.py
xoinvader/tests/test_init.py
xoinvader/tests/test_keys.py
xoinvader/tests/test_level.py
xoinvader/tests/test_scoreboard.py
xoinvader/tests/test_utils.py
xoinvader/tests/test_weapon.py
xoinvader/utils.py
xoinvader/weapon.py
xoinvader-0.2.0.dist-info/entry_points.txt
xoinvader-0.2.0.dist-info/LICENSE
xoinvader-0.2.0.dist-info/WHEEL
xoinvader-0.2.0.dist-info/METADATA
xoinvader-0.2.0.dist-info/RECORD
