Metadata-Version: 2.1
Name: xoinvader
Version: 0.2.0
Summary: (not so) small python curses space game
Home-page: https://github.com/pkulev/xoinvader
License: MIT
Keywords: curses,space,game
Author: Pavel Kulyov
Author-email: kulyov.pavel@gmail.com
Requires-Python: >=3.7,<4.0
Classifier: Development Status :: 3 - Alpha
Classifier: Environment :: Console :: Curses
Classifier: Environment :: X11 Applications
Classifier: Intended Audience :: Developers
Classifier: Intended Audience :: Education
Classifier: Intended Audience :: End Users/Desktop
Classifier: License :: OSI Approved :: MIT License
Classifier: Operating System :: POSIX :: Linux
Classifier: Programming Language :: Python :: 3
Classifier: Programming Language :: Python :: 3.7
Classifier: Programming Language :: Python :: 3.8
Classifier: Programming Language :: Python :: Implementation :: CPython
Classifier: Topic :: Games/Entertainment :: Arcade
Classifier: Topic :: Software Development :: Libraries :: pygame
Requires-Dist: eaf (>=0.2,<0.3)
Requires-Dist: toml (>=0.10,<0.11)
Requires-Dist: xo1 (>=0.1,<0.2)
Project-URL: Documentation, http://mmap.me/
Project-URL: Repository, https://github.com/pkulev/xoinvader
